vecc-0.12.dist-info/RECORD
vecc-0.12.dist-info/METADATA
vecc-0.12.dist-info/entry_points.txt
vecc-0.12.dist-info/metadata.json
vecc-0.12.dist-info/DESCRIPTION.rst
vecc-0.12.dist-info/top_level.txt
vecc-0.12.dist-info/WHEEL
vecc/tests.py
vecc/core.py
vecc/providers.py
vecc/vecc.py
vecc/__init__.py
